deepdos/__init__.py
deepdos/__main__.py
deepdos/args.py
deepdos/conf.py
deepdos/data.py
deepdos/firewall.py
deepdos/iptables.py
deepdos/utils.py
deepdos/external/CICFlowMeter-4.0/LICENSE.txt
deepdos/external/CICFlowMeter-4.0/README.md
deepdos/external/CICFlowMeter-4.0/bin/CICFlowMeter
deepdos/external/CICFlowMeter-4.0/bin/CICFlowMeter.bat
deepdos/external/CICFlowMeter-4.0/bin/cfm
deepdos/external/CICFlowMeter-4.0/bin/cfm.bat
deepdos/external/CICFlowMeter-4.0/bin/logs/debug
deepdos/external/CICFlowMeter-4.0/bin/logs/info.log
deepdos/external/CICFlowMeter-4.0/lib/CICFlowMeter-4.0.jar
deepdos/external/CICFlowMeter-4.0/lib/animal-sniffer-annotations-1.14.jar
deepdos/external/CICFlowMeter-4.0/lib/checker-compat-qual-2.0.0.jar
deepdos/external/CICFlowMeter-4.0/lib/commons-io-2.5.jar
deepdos/external/CICFlowMeter-4.0/lib/commons-lang3-3.6.jar
deepdos/external/CICFlowMeter-4.0/lib/commons-math3-3.5.jar
deepdos/external/CICFlowMeter-4.0/lib/error_prone_annotations-2.1.3.jar
deepdos/external/CICFlowMeter-4.0/lib/guava-23.6-jre.jar
deepdos/external/CICFlowMeter-4.0/lib/hamcrest-core-1.3.jar
deepdos/external/CICFlowMeter-4.0/lib/j2objc-annotations-1.1.jar
deepdos/external/CICFlowMeter-4.0/lib/java-cup-0.11a.jar
deepdos/external/CICFlowMeter-4.0/lib/jfreechart-1.5.0.jar
deepdos/external/CICFlowMeter-4.0/lib/jnetpcap-1.4.1.jar
deepdos/external/CICFlowMeter-4.0/lib/jsr305-1.3.9.jar
deepdos/external/CICFlowMeter-4.0/lib/junit-4.12.jar
deepdos/external/CICFlowMeter-4.0/lib/log4j-1.2.17.jar
deepdos/external/CICFlowMeter-4.0/lib/log4j-api-2.11.0.jar
deepdos/external/CICFlowMeter-4.0/lib/log4j-core-2.11.0.jar
deepdos/external/CICFlowMeter-4.0/lib/slf4j-api-1.7.25.jar
deepdos/external/CICFlowMeter-4.0/lib/slf4j-log4j12-1.7.25.jar
deepdos/external/CICFlowMeter-4.0/lib/tika-core-1.17.jar
deepdos/external/CICFlowMeter-4.0/lib/weka-stable-3.6.14.jar
deepdos/external/CICFlowMeter-4.0/lib/native/jnetpcap-pcap100.dll
deepdos/external/CICFlowMeter-4.0/lib/native/jnetpcap.dll
deepdos-0.9.95.dist-info/LICENSE
deepdos-0.9.95.dist-info/METADATA
deepdos-0.9.95.dist-info/WHEEL
deepdos-0.9.95.dist-info/entry_points.txt
deepdos-0.9.95.dist-info/top_level.txt
deepdos-0.9.95.dist-info/RECORD
