Metadata-Version: 2.1
Name: deepdos
Version: 0.9.95
Summary: A machine learning/AI based approach to protecting your devices against ddos attacks
Home-page: https://github.com/C3NZ/deepdos
Author: C3NZ
Author-email: cenz@cenz.io
License: MIT
Platform: UNKNOWN
Classifier: License :: OSI Approved :: MIT License
Classifier: Topic :: Security
Classifier: Environment :: Console
Classifier: Operating System :: POSIX :: Linux
Classifier: Operating System :: MacOS
Classifier: Development Status :: 2 - Pre-Alpha
Requires-Dist: numpy (==1.17.2)
Requires-Dist: pandas (==0.25.1)
Requires-Dist: psutil (==5.6.3)
Requires-Dist: python-iptables (==0.14.0)
Requires-Dist: scikit-learn (==0.21.3)
Requires-Dist: wheel (==0.32.3)
